ashok_weather_reporter/cli.py
ashok_weather_reporter/utils.py
ashok_weather_reporter-1.0.1.dist-info/LICENSE
ashok_weather_reporter-1.0.1.dist-info/METADATA
ashok_weather_reporter-1.0.1.dist-info/WHEEL
ashok_weather_reporter-1.0.1.dist-info/entry_points.txt
ashok_weather_reporter-1.0.1.dist-info/top_level.txt
ashok_weather_reporter-1.0.1.dist-info/RECORD
