Metadata-Version: 2.1
Name: ashok-weather-reporter
Version: 1.0.1
Summary: A Python package to get weather reports for any location.
Home-page: UNKNOWN
Author: Ashok Londhe
Author-email: ashoklondhe.in@gmail.com
License: Internal, Proprietary
Platform: UNKNOWN
Classifier: Programming Language :: Python :: 3
Classifier: Programming Language :: Python :: 3.7
Requires-Dist: requests
